PTN/__init__.py
PTN/extras.py
PTN/parse.py
PTN/patterns.py
PTN/post.py
parse_torrent_title-2.8.1.dist-info/LICENSE
parse_torrent_title-2.8.1.dist-info/METADATA
parse_torrent_title-2.8.1.dist-info/WHEEL
parse_torrent_title-2.8.1.dist-info/top_level.txt
parse_torrent_title-2.8.1.dist-info/RECORD
