Metadata-Version: 2.1
Name: parse-torrent-title
Version: 2.8.1
Summary: Extract media information from torrent-like filename
Home-page: https://github.com/platelminto/parse-torrent-title
Author: Giorgio Momigliano
Author-email: gmomigliano@protonmail.com
License: MIT
Keywords: parse parser torrent torrents name names proper rename movie movies tv show shows series extract find quality group codec audio resolution title season episode year information filename filenames file files meaningful
Platform: UNKNOWN
Classifier: Development Status :: 5 - Production/Stable
Classifier: Intended Audience :: Developers
Classifier: License :: OSI Approved :: MIT License
Classifier: Natural Language :: English
Classifier: Topic :: Text Processing
